[
    {
        "model": "app_api.RareUser",
        "pk": 1,
        "fields": {
            "bio": "I like to write.",
            "profile_image_url": "https://cdn-icons-png.flaticon.com/512/714/714036.png",
            "created_on": "2020-08-28",
            "active": true,
            "user": 1
        }
    }, 
    {
        "model": "app_api.RareUser",
        "pk": 2,
        "fields": {
            "bio": "Woof.",
            "profile_image_url": "https://cdn3.iconfinder.com/data/icons/avatars-9/145/Avatar_Dog-512.png",
            "created_on": "2022-08-15",
            "active": true,
            "user": 2
        }
    }
]